bl3d/__init__.py
bl3d/py.typed
bl3d-0.4.2.dist-info/LICENSE.md
bl3d-0.4.2.dist-info/METADATA
bl3d-0.4.2.dist-info/WHEEL
bl3d-0.4.2.dist-info/RECORD
